AUTHORS
ChangeLog
LICENSE
README.md
requirements.txt
setup.cfg
setup.py
test-requirements.txt
tox.ini
doc/job.md
doc/view.md
jcli/__init__.py
jcli/cmd.py
jcli/config.py
jcli/core.py
jcli/errors.py
jcli/parse.py
jcli.egg-info/PKG-INFO
jcli.egg-info/SOURCES.txt
jcli.egg-info/dependency_links.txt
jcli.egg-info/entry_points.txt
jcli.egg-info/not-zip-safe
jcli.egg-info/pbr.json
jcli.egg-info/requires.txt
jcli.egg-info/top_level.txt
jcli/executor/__init__.py
jcli/executor/job.py
jcli/executor/node.py
jcli/executor/plugin.py
jcli/executor/server.py
jcli/executor/view.py